rfb_driver_bms/__init__.py
rfb_driver_bms/__version__.py
rfb_driver_bms/context.py
rfb_driver_bms/drv_bms.py
rfb_driver_bms-0.0.1.dist-info/LICENSE.txt
rfb_driver_bms-0.0.1.dist-info/METADATA
rfb_driver_bms-0.0.1.dist-info/WHEEL
rfb_driver_bms-0.0.1.dist-info/top_level.txt
rfb_driver_bms-0.0.1.dist-info/RECORD
