Metadata-Version: 2.1
Name: rfb-driver-bms
Version: 0.0.1
Summary: Driver to mannage the bms hardware and get measures from it.
Author-email: Raldea <r.aldea.csic+pypi@gmail.com>, Marius Crisan <mariuscrsn+pypi@gmail.com>, Pablo Pastor <pastorpflores+pypi@gmail.com>, Javier Sanz <javiersanzmoline@gmail.com>, Luis Roche <luis.roche@hotmail.com>
License: GNU GENERAL PUBLIC LICENSE
Project-URL: Homepage, https://github.com/GIDEF-RFB/Battery-Cycler-Drivers
Project-URL: Bug Reports, https://github.com/GIDEF-RFB/Battery-Cycler-Drivers/issues
Project-URL: Bug Tracker, https://github.com/GIDEF-RFB/Battery-Cycler-Drivers/issues
Project-URL: Source, https://github.com/GIDEF-RFB/Battery-Cycler-Drivers/tree/develop/code/drv_bms
Project-URL: Funding, https://donate.pypi.org
Keywords: Battery Mannagement Systems,Embedded Systems,Can,Redox flow battery,Logger system
Classifier: Development Status :: 3 - Alpha
Classifier: Topic :: Software Development :: Embedded Systems
Classifier: Operating System :: OS Independent
Classifier: License :: OSI Approved :: GNU Affero General Public License v3
Classifier: Programming Language :: Python :: 3
Classifier: Programming Language :: Python :: 3.7
Classifier: Programming Language :: Python :: 3.8
Classifier: Programming Language :: Python :: 3.9
Classifier: Programming Language :: Python :: 3.10
Classifier: Programming Language :: Python :: 3 :: Only
Requires-Python: >=3.7
License-File: LICENSE.txt
Requires-Dist: rfb-logger-tool >=0.0.1
Requires-Dist: rfb-config-tool >=0.0.1
Requires-Dist: rfb-shared-tool >=0.0.1
Requires-Dist: rfb-can-sniffer >=0.0.1
Requires-Dist: rfb-driver-bases >=0.0.1
